README.md
setup.py
ytsentimentanalysis/YTSentimentAnalysis.py
ytsentimentanalysis/__init__.py
ytsentimentanalysis.egg-info/PKG-INFO
ytsentimentanalysis.egg-info/SOURCES.txt
ytsentimentanalysis.egg-info/dependency_links.txt
ytsentimentanalysis.egg-info/requires.txt
ytsentimentanalysis.egg-info/top_level.txt