Metadata-Version: 2.1
Name: ytsentimentanalysis
Version: 0.0.1
Summary: Youtube Sentiment Analysis
Home-page: UNKNOWN
Author: Youssef EL ASERY
Author-email: joseph.elasery@gmail.com
License: MIT License
Keywords: python,first package
Platform: UNKNOWN
Classifier: Intended Audience :: Education
Classifier: Programming Language :: Python :: 2
Classifier: Programming Language :: Python :: 3
Classifier: Operating System :: MacOS :: MacOS X
Classifier: Operating System :: Microsoft :: Windows
